yt_shorts_grab/__init__.py
yt_shorts_grab/grabber.py
yt_shorts_grab-0.1.0.dist-info/METADATA
yt_shorts_grab-0.1.0.dist-info/WHEEL
yt_shorts_grab-0.1.0.dist-info/top_level.txt
yt_shorts_grab-0.1.0.dist-info/RECORD
